BeautifulReport/BeautifulReport.py
BeautifulReport/__init__.py
BeautifulReport/template/template.html
BeautifulReport/template/theme.json
BeautifulReport/template/theme_candy.json
BeautifulReport/template/theme_cyan.json
BeautifulReport/template/theme_default.json
BeautifulReport/template/theme_memories.json
BeautifulReport_fix-0.1.3.dist-info/LICENSE
BeautifulReport_fix-0.1.3.dist-info/METADATA
BeautifulReport_fix-0.1.3.dist-info/WHEEL
BeautifulReport_fix-0.1.3.dist-info/top_level.txt
BeautifulReport_fix-0.1.3.dist-info/RECORD
