Metadata-Version: 2.1
Name: BeautifulReport-fix
Version: 0.1.3
Summary: unittest自动化测试的可视化报告模板-修复源版本
Home-page: https://github.com/xiaomaipian/BeautifulReport-fix
Author: xiaomaipian
Author-email: ice_emp@163.com
Classifier: Programming Language :: Python :: 3
Classifier: License :: OSI Approved :: MIT License
Classifier: Operating System :: OS Independent
License-File: LICENSE
